statedump
